python_rc-0.4.1.data/scripts/rc
rc/__init__.py
rc/disk.py
rc/exception.py
rc/firewall.py
rc/image.py
rc/machine.py
rc/util.py
rc/cli/__init__.py
rc/cli/config.py
rc/provider/__init__.py
rc/provider/aws.py
rc/provider/azure.py
rc/provider/digitalocean.py
rc/provider/gcloud.py
rc/provider/kubernetes.py
rc/provider/openstack.py
rc/provider/vagrant.py
rc/test/__init__.py
rc/test/test_aws.py
rc/test/test_azure.py
rc/test/test_concurrent.py
rc/test/test_gcloud.py
rc/test/test_run.py
rc/test/util.py
python_rc-0.4.1.dist-info/LICENSE
python_rc-0.4.1.dist-info/METADATA
python_rc-0.4.1.dist-info/WHEEL
python_rc-0.4.1.dist-info/top_level.txt
python_rc-0.4.1.dist-info/RECORD
