Metadata-Version: 2.1
Name: python-rc
Version: 0.4.1
Summary: Python remote control library for programmatically control remote machines
Home-page: https://github.com/ailisp/python-rc
Author: Bo Yao
Author-email: icerove@gmail.com
License: UNKNOWN
Platform: UNKNOWN
Classifier: Programming Language :: Python :: 3
Classifier: Development Status :: 3 - Alpha
Classifier: Intended Audience :: Developers
Classifier: Intended Audience :: System Administrators
Classifier: License :: OSI Approved :: BSD License
Classifier: Operating System :: MacOS :: MacOS X
Classifier: Operating System :: POSIX :: Linux
Classifier: Topic :: System :: Clustering
Classifier: Topic :: System :: Distributed Computing
Classifier: Topic :: System :: Installation/Setup
Classifier: Topic :: System :: Systems Administration
Requires-Python: >=3.6
Requires-Dist: retry
Requires-Dist: PyYAML
Requires-Dist: humanfriendly
Requires-Dist: libtmux
Requires-Dist: py-term
Requires-Dist: pytimeparse
